{"pvmek@mail.ru": {"cookies": [{"version": 0, "name": "h", "value": "1", "port": null, "port_specified": false, "domain": ".login.vk.com", "domain_specified": true, "domain_initial_dot": false, "path": "/", "path_specified": true, "secure": true, "expires": null, "discard": false, "comment": null, "comment_url": null, "rfc2109": false, "rest": {"HttpOnly": null}}, {"version": 0, "name": "l", "value": "2912995", "port": null, "port_specified": false, "domain": ".login.vk.com", "domain_specified": true, "domain_initial_dot": false, "path": "/", "path_specified": true, "secure": true, "expires": null, "discard": false, "comment": null, "comment_url": null, "rfc2109": false, "rest": {"HttpOnly": null}}, {"version": 0, "name": "p", "value": "508ad52721435bda215f24503f071d4fbe8fa60e3caa05ed33f2642993f82", "port": null, "port_specified": false, "domain": ".login.vk.com", "domain_specified": true, "domain_initial_dot": false, "path": "/", "path_specified": true, "secure": true, "expires": null, "discard": false, "comment": null, "comment_url": null, "rfc2109": false, "rest": {"HttpOnly": null}}, {"version": 0, "name": "s", "value": "1", "port": null, "port_specified": false, "domain": ".login.vk.com", "domain_specified": true, "domain_initial_dot": false, "path": "/", "path_specified": true, "secure": true, "expires": null, "discard": false, "comment": null, "comment_url": null, "rfc2109": false, "rest": {"HttpOnly": null}}, {"version": 0, "name": "remixlang", "value": "0", "port": null, "port_specified": false, "domain": ".vk.com", "domain_specified": true, "domain_initial_dot": true, "path": "/", "path_specified": true, "secure": false, "expires": null, "discard": false, "comment": null, "comment_url": null, "rfc2109": false, "rest": {}}, {"version": 0, "name": "remixsid", "value": "1e467870ac1de13c09de909e88c6bffbbd994b92d512b1ae29ad86bf1eb57", "port": null, "port_specified": false, "domain": ".vk.com", "domain_specified": true, "domain_initial_dot": true, "path": "/", "path_specified": true, "secure": true, "expires": null, "discard": false, "comment": null, "comment_url": null, "rfc2109": false, "rest": {"HttpOnly": null}}, {"version": 0, "name": "remixstid", "value": "1859983238_6e689b73b59cd4c235", "port": null, "port_specified": false, "domain": ".vk.com", "domain_specified": true, "domain_initial_dot": true, "path": "/", "path_specified": true, "secure": true, "expires": null, "discard": false, "comment": null, "comment_url": null, "rfc2109": false, "rest": {}}, {"version": 0, "name": "remixusid", "value": "ODY1M2I3ZmQ5YmVjOWEwNzcxY2M2M2I0", "port": null, "port_specified": false, "domain": ".vk.com", "domain_specified": true, "domain_initial_dot": true, "path": "/", "path_specified": true, "secure": true, "expires": null, "discard": false, "comment": null, "comment_url": null, "rfc2109": false, "rest": {"HttpOnly": null}}], "token": {"app2895443": {"scope_33554431": {"access_token": "8edbc0a08793583b6eea0eb90a5b2a108a35ba75a717d78d6528ec58e81ec7170cdde62f52eafe5e909d3", "expires_in": "0", "user_id": "2912995", "email": "pvmek@mail.ru"}}}}}